easy_async/__init__.py
easy_async-0.1.0.dist-info/LICENSE
easy_async-0.1.0.dist-info/METADATA
easy_async-0.1.0.dist-info/WHEEL
easy_async-0.1.0.dist-info/RECORD
