Metadata-Version: 2.1
Name: easy-async
Version: 0.1.0
Summary: Please forget you are using asyncio
Home-page: https://github.com/majoson-chen/easy-async
Keywords: asyncio,async,easy,easy-async
Author: Majoson
Author-email: majoson@qq.com
Requires-Python: >=3.6,<4.0
Classifier: License :: OSI Approved :: MIT License
Classifier: Operating System :: OS Independent
Classifier: Programming Language :: Python :: 3
Classifier: Programming Language :: Python :: 3.6
Classifier: Programming Language :: Python :: 3.7
Classifier: Programming Language :: Python :: 3.8
Classifier: Programming Language :: Python :: 3.9
Classifier: Programming Language :: Python :: 3.10
Classifier: Programming Language :: Python :: 3.11
Project-URL: Repository, https://github.com/majoson-chen/easy-async
